{

  "name":"wrinche",
  "description":"Modern, powerful and user friendly CMS.",
  "version":"1.0.0",
  "domain":"/",
  "charset":"UTF-8",

  "requirements": {
    "php-version":7.0
  },

  "env": {
    "production":false,
    "development":true
  },

  "locale": {
    "timezone":"UTC",
    "language":"en"
  },

  "paths": {
    "assets":"assets/",
    "styles":"styles/",
    "scripts":"scripts/",
    "fonts":"fonts/",
    "vendor":"vendor/"
  },

  "vendor": {
    "styles": {
      "formstone-dropdown":"dropdown.min.css"
    },
    "scripts": {
      "jquery":"jquery.min.js",
      "formstone-core":"core.min.js",
      "formstone-dropdown":"dropdown.min.js"
    }
  },

  "installed":false

}